{"files":{"packages/spinner/dist/index.css.map":{"size":1336,"mtime_nanos":1782741990830856700,"mode":420,"is_dir":false},"packages/spinner/dist/index.cjs":{"size":1825,"mtime_nanos":1782741990667223300,"mode":420,"is_dir":false},"packages/spinner/dist/index.d.ts":{"size":399,"mtime_nanos":1782742004399202800,"mode":420,"is_dir":false},"packages/spinner/dist":{"size":0,"mtime_nanos":0,"mode":0,"is_dir":true},"packages/spinner/dist/index.js":{"size":721,"mtime_nanos":1782741990828861400,"mode":420,"is_dir":false},"packages/spinner/dist/index.css":{"size":757,"mtime_nanos":1782741990828861400,"mode":420,"is_dir":false},"packages/spinner/.turbo/turbo-build.log":{"size":1092,"mtime_nanos":1782742005583718900,"mode":420,"is_dir":false},"packages/spinner/dist/index.js.map":{"size":1254,"mtime_nanos":1782741990830856700,"mode":420,"is_dir":false},"packages/spinner/dist/index.cjs.map":{"size":1461,"mtime_nanos":1782741990668221000,"mode":420,"is_dir":false},"packages/spinner/dist/index.d.cts":{"size":399,"mtime_nanos":1782742004399202800,"mode":420,"is_dir":false}},"order":["packages/spinner/.turbo/turbo-build.log","packages/spinner/dist","packages/spinner/dist/index.cjs","packages/spinner/dist/index.cjs.map","packages/spinner/dist/index.css","packages/spinner/dist/index.css.map","packages/spinner/dist/index.d.cts","packages/spinner/dist/index.d.ts","packages/spinner/dist/index.js","packages/spinner/dist/index.js.map"]}